cf_bypass/__init__.py
cf_bypass/auto.py
cf_bypass/base_detector.py
cf_bypass/cf_captcha_detector.py
cf_bypass/images/cf_logo.png
cf_bypass/images/cf_logo_dark.png
cf_bypass/images/cf_popup.png
cf_bypass/images/cf_popup_dark.png
cf_bypass-0.1.1.dist-info/LICENSE
cf_bypass-0.1.1.dist-info/METADATA
cf_bypass-0.1.1.dist-info/WHEEL
cf_bypass-0.1.1.dist-info/RECORD
