Metadata-Version: 2.1
Name: cf-bypass
Version: 0.1.1
Summary: A tool for bypassing Cloudflare CAPTCHA
Home-page: https://github.com/tamnguyenvan/cf_bypass
License: MIT
Author: Tam Nguyen
Author-email: tamnv.work@gmail.com
Requires-Python: >=3.9,<4.0
Classifier: License :: OSI Approved :: MIT License
Classifier: Programming Language :: Python :: 3
Classifier: Programming Language :: Python :: 3.9
Classifier: Programming Language :: Python :: 3.10
Classifier: Programming Language :: Python :: 3.11
Classifier: Programming Language :: Python :: 3.12
Requires-Dist: Pillow (>=8.2.0,<9.0.0)
Requires-Dist: numpy (>=1.20.0,<2.0.0)
Requires-Dist: opencv-python (>=4.5.1.48,<5.0.0.0)
Requires-Dist: pyautogui (>=0.9.36,<0.10.0)
